pynori/__init__.py
pynori/char_unicode.py
pynori/config.ini
pynori/decompound_token.py
pynori/dictionary_token.py
pynori/korean_analyzer.py
pynori/korean_posstop_filter.py
pynori/korean_tokenizer.py
pynori/multiprocessor.py
pynori/pos.py
pynori/post_processing.py
pynori/pre_processing.py
pynori/synonym_graph_filter.py
pynori/token.py
pynori/token_attribute.py
pynori/utils.py
pynori/dict/__init__.py
pynori/dict/character_definition.py
pynori/dict/connection_costs.py
pynori/dict/dictionary.py
pynori/dict/known_dictionary.py
pynori/dict/trie.py
pynori/dict/unknown_dictionary.py
pynori/dict/user_dictionary.py
pynori/resources/synonyms.txt
pynori/resources/userdict_ko.txt
pynori/resources/mecab-ko-dic-2.1.1-20180720/.keep
pynori/resources/mecab-ko-dic-2.1.1-20180720/AUTHORS
pynori/resources/mecab-ko-dic-2.1.1-20180720/COPYING
pynori/resources/mecab-ko-dic-2.1.1-20180720/ChangeLog
pynori/resources/mecab-ko-dic-2.1.1-20180720/CoinedWord.csv
pynori/resources/mecab-ko-dic-2.1.1-20180720/EC.csv
pynori/resources/mecab-ko-dic-2.1.1-20180720/EF.csv
pynori/resources/mecab-ko-dic-2.1.1-20180720/EP.csv
pynori/resources/mecab-ko-dic-2.1.1-20180720/ETM.csv
pynori/resources/mecab-ko-dic-2.1.1-20180720/ETN.csv
pynori/resources/mecab-ko-dic-2.1.1-20180720/Foreign.csv
pynori/resources/mecab-ko-dic-2.1.1-20180720/Group.csv
pynori/resources/mecab-ko-dic-2.1.1-20180720/Hanja.csv
pynori/resources/mecab-ko-dic-2.1.1-20180720/IC.csv
pynori/resources/mecab-ko-dic-2.1.1-20180720/INSTALL
pynori/resources/mecab-ko-dic-2.1.1-20180720/Inflect.csv
pynori/resources/mecab-ko-dic-2.1.1-20180720/J.csv
pynori/resources/mecab-ko-dic-2.1.1-20180720/MAG.csv
pynori/resources/mecab-ko-dic-2.1.1-20180720/MAJ.csv
pynori/resources/mecab-ko-dic-2.1.1-20180720/MM.csv
pynori/resources/mecab-ko-dic-2.1.1-20180720/Makefile.am
pynori/resources/mecab-ko-dic-2.1.1-20180720/Makefile.in
pynori/resources/mecab-ko-dic-2.1.1-20180720/NEWS
pynori/resources/mecab-ko-dic-2.1.1-20180720/NNB.csv
pynori-0.2.4.dist-info/LICENSE
pynori-0.2.4.dist-info/METADATA
pynori-0.2.4.dist-info/WHEEL
pynori-0.2.4.dist-info/top_level.txt
pynori-0.2.4.dist-info/RECORD
