Metadata-Version: 2.1
Name: pynori
Version: 0.2.4
Summary: Lucene Nori, Korean Mopological Analyzer, in Python
Home-page: https://github.com/gritmind/python-nori
Author: Yeongsu Kim
Author-email: gritmind@naver.com
License: Apache 2.0
Platform: UNKNOWN
Classifier: Development Status :: 4 - Beta
Classifier: Programming Language :: Python :: 3.7
Classifier: Programming Language :: Python :: 3.6
Classifier: Programming Language :: Python :: 3.5
Classifier: License :: OSI Approved :: Apache Software License
License-File: LICENSE
Requires-Dist: cython
